mockpipe/__init__.py
mockpipe/__main__.py
mockpipe/_version.py
mockpipe/action.py
mockpipe/config.py
mockpipe/db_connector.py
mockpipe/exceptions.py
mockpipe/exporter.py
mockpipe/field.py
mockpipe/imposter.py
mockpipe/mockpipe.py
mockpipe/table.py
mockpipe-0.0.3.dist-info/LICENSE
mockpipe-0.0.3.dist-info/METADATA
mockpipe-0.0.3.dist-info/WHEEL
mockpipe-0.0.3.dist-info/entry_points.txt
mockpipe-0.0.3.dist-info/top_level.txt
mockpipe-0.0.3.dist-info/RECORD
