Metadata-Version: 2.1
Name: mockpipe
Version: 0.0.3
Summary: Dummy data generator focusing on customisability and maintained relationships for mocking data pipelines
Author: BenskiBoy
Project-URL: Source, https://github.com/BenskiBoy/mockpipe
Project-URL: Bug Tracker, https://github.com/BenskiBoy/mockpipe/issues
Project-URL: Changes, https://github.com/BenskiBoy/mockpipe/blob/master/CHANGELOG.md
Keywords: mocking data faker testing generator pipeline pipe
Classifier: License :: OSI Approved :: MIT License
Classifier: Programming Language :: Python :: 3.8
Classifier: Programming Language :: Python :: 3.9
Classifier: Programming Language :: Python :: 3.10
Classifier: Programming Language :: Python :: 3.11
Classifier: Programming Language :: Python :: 3.12
Classifier: Programming Language :: Python :: 3.13
Classifier: Topic :: Software Development :: Libraries :: Python Modules
Classifier: Topic :: Software Development :: Testing
Classifier: Topic :: Utilities
Requires-Python: >=3.8
License-File: LICENSE
Requires-Dist: black==24.10.0
Requires-Dist: click==8.1.7
Requires-Dist: duckdb==1.0.0
Requires-Dist: Faker==26.0.0
Requires-Dist: faker-commerce==1.0.4
Requires-Dist: pytest==8.3.2
Requires-Dist: pytest-cov==5.0.0
Requires-Dist: PyYAML==6.0.1
